kiara_plugin/html/__init__.py
kiara_plugin/html/data_types.py
kiara_plugin/html/defaults.py
kiara_plugin/html/py.typed
kiara_plugin/html/version.txt
kiara_plugin/html/interfaces/__init__.py
kiara_plugin/html/interfaces/cli/__init__.py
kiara_plugin/html/models/__init__.py
kiara_plugin/html/modules/__init__.py
kiara_plugin/html/modules/core_types.py
kiara_plugin/html/modules/included_types.py
kiara_plugin/html/modules/tabular.py
kiara_plugin/html/pipelines/.gitkeep
kiara_plugin/html/pipelines/__init__.py
kiara_plugin/html/renderers/__init__.py
kiara_plugin/html/renderers/lineage.py
kiara_plugin/html/resources/.gitkeep
kiara_plugin/html/resources/templates/lineage/lineage.html.j2
kiara_plugin/html/resources/templates/lineage/assets/json-fomatter.js
kiara_plugin/html/resources/templates/lineage/assets/msgpack.js
kiara_plugin.html-0.5.0.dist-info/AUTHORS.md
kiara_plugin.html-0.5.0.dist-info/LICENSE
kiara_plugin.html-0.5.0.dist-info/METADATA
kiara_plugin.html-0.5.0.dist-info/WHEEL
kiara_plugin.html-0.5.0.dist-info/entry_points.txt
kiara_plugin.html-0.5.0.dist-info/top_level.txt
kiara_plugin.html-0.5.0.dist-info/RECORD
