Metadata-Version: 2.1
Name: kiara-plugin.html
Version: 0.5.0
Summary: Kiara plugin for html-related tasks.
Author-email: Markus Binsteiner <markus@frkl.io>
License: MPL-2.0
Project-URL: homepage, https://github.com/DHARPA-Project/kiara_plugin.html
Project-URL: documentation, https://DHARPA-Project.github.io/kiara_plugin.html
Project-URL: repository, https://github.com/DHARPA-Project/kiara_plugin.html
Keywords: kiara
Classifier: Programming Language :: Python :: 3
Classifier: Development Status :: 3 - Alpha
Classifier: License :: OSI Approved :: Mozilla Public License 2.0 (MPL 2.0)
Classifier: Programming Language :: Python
Classifier: Programming Language :: Python :: 3
Classifier: Programming Language :: Python :: 3 :: Only
Classifier: Programming Language :: Python :: 3.8
Classifier: Programming Language :: Python :: 3.9
Classifier: Programming Language :: Python :: 3.10
Classifier: Programming Language :: Python :: 3.11
Classifier: Programming Language :: Python :: 3.12
Requires-Python: >=3.8
License-File: LICENSE
License-File: AUTHORS.md
Requires-Dist: kiara <0.6.0,>=0.5.3
Requires-Dist: kiara-plugin.core-types <0.6.0,>=0.5.0
Requires-Dist: kiara-plugin.tabular <0.6.0,>=0.5.0
Requires-Dist: json2html >=1.3.0
Requires-Dist: markdown >=3.2.1
Requires-Dist: pymdown-extensions >=9.9
Requires-Dist: airium >=0.2.3
Provides-Extra: all_plugins
Requires-Dist: kiara-plugin.core-types ; extra == 'all_plugins'
Requires-Dist: kiara-plugin.tabular ; extra == 'all_plugins'
Requires-Dist: kiara-plugin.onboarding ; extra == 'all_plugins'
Requires-Dist: kiara-plugin.network-analysis ; extra == 'all_plugins'
Requires-Dist: kiara-plugin.language-processing ; extra == 'all_plugins'
Requires-Dist: kiara-plugin.jupyter ; extra == 'all_plugins'
Requires-Dist: kiara-plugin.streamlit ; extra == 'all_plugins'
Provides-Extra: dev_all
Requires-Dist: kiara[dev_all] ; extra == 'dev_all'
Provides-Extra: dev_documentation
Requires-Dist: kiara[dev_documentation] ; extra == 'dev_documentation'
Provides-Extra: dev_testing
Requires-Dist: kiara[dev_testing] ; extra == 'dev_testing'
Provides-Extra: dev_utils
Requires-Dist: kiara[dev_utils] ; extra == 'dev_utils'
Provides-Extra: graph_viz
Requires-Dist: pygraphviz >=1.10 ; extra == 'graph_viz'
Provides-Extra: streamlit
Requires-Dist: kiara-plugin.streamlit ; extra == 'streamlit'
